verilog-session/task2/UpCounter_4bit.v
module UpCounter_4bit(enable, reset, clk, count);
  input enable, reset, clk;
  output reg[3:0] count;

  always @(posedge clk) begin
    if(reset) count = 0;
    if(enable && !reset) count++;
  end
endmodule

processor/clock/Clock.v
module Clock(clk);
  output reg clk;

  initial begin
    clk = 1;
    forever begin
      #5 clk = ~clk;
    end
  end
endmodule

verilog-session/task2/TestUpCounter_4bit.v
`include "UpCounter_4bit.v"
`include "./clock/Clock.v"

module TestUpCounter_4bit;
  // build the circuit
  reg enable, reset;
  wire clk;
  wire[3:0] count;

  Clock clock(clk);
  UpCounter_4bit counter(enable, reset, clk, count);

  // test
  initial begin
    #8
    reset = 1;
    enable = 1;

    #4
    reset = 0;

    #500
    $finish;
  end

  initial begin
    #52
    enable = 0;
    #10
    enable = 1;
  end

  // gtkWave
  initial begin 
    $dumpfile("TestUpCounter_4bit.vcd");
    $dumpvars(0, TestUpCounter_4bit);
  end

  // monitor
  initial begin
    $display();
    $display("********************  Test UpCounter_4bit  ********************");
    $display("\tEnable\tReset\tcount");
    $monitor("\t%b\t%b\t%d", enable, reset, count); 
  end



endmodule

verilog-session/task2/TestUpCounter_4bit.vcd
$date
	Sun Oct 13 16:59:05 2024
$end
$version
	Icarus Verilog
$end
$timescale
	1s
$end
$scope module TestUpCounter_4bit $end
$var wire 4 ! count [3:0] $end
$var wire 1 " clk $end
$var reg 1 # enable $end
$var reg 1 $ reset $end
$scope module clock $end
$var reg 1 " clk $end
$upscope $end
$scope module counter $end
$var wire 1 " clk $end
$var wire 1 # enable $end
$var wire 1 $ reset $end
$var reg 4 % count [3:0] $end
$upscope $end
$upscope $end
$enddefinitions $end
$comment Show the parameter values. $end
$dumpall
$end
#0
$dumpvars
bx %
x$
x#
1"
bx !
$end
#5
0"
#8
1#
1$
#10
b0 !
b0 %
1"
#12
0$
#15
0"
#20
b1 !
b1 %
1"
#25
0"
#30
b10 !
b10 %
1"
#35
0"
#40
b11 !
b11 %
1"
#45
0"
#50
b100 !
b100 %
1"
#52
0#
#55
0"
#60
1"
#62
1#
#65
0"
#70
b101 !
b101 %
1"
#75
0"
#80
b110 !
b110 %
1"
#85
0"
#90
b111 !
b111 %
1"
#95
0"
#100
b1000 !
b1000 %
1"
#105
0"
#110
b1001 !
b1001 %
1"
#115
0"
#120
b1010 !
b1010 %
1"
#125
0"
#130
b1011 !
b1011 %
1"
#135
0"
#140
b1100 !
b1100 %
1"
#145
0"
#150
b1101 !
b1101 %
1"
#155
0"
#160
b1110 !
b1110 %
1"
#165
0"
#170
b1111 !
b1111 %
1"
#175
0"
#180
b0 !
b0 %
1"
#185
0"
#190
b1 !
b1 %
1"
#195
0"
#200
b10 !
b10 %
1"
#205
0"
#210
b11 !
b11 %
1"
#215
0"
#220
b100 !
b100 %
1"
#225
0"
#230
b101 !
b101 %
1"
#235
0"
#240
b110 !
b110 %
1"
#245
0"
#250
b111 !
b111 %
1"
#255
0"
#260
b1000 !
b1000 %
1"
#265
0"
#270
b1001 !
b1001 %
1"
#275
0"
#280
b1010 !
b1010 %
1"
#285
0"
#290
b1011 !
b1011 %
1"
#295
0"
#300
b1100 !
b1100 %
1"
#305
0"
#310
b1101 !
b1101 %
1"
#315
0"
#320
b1110 !
b1110 %
1"
#325
0"
#330
b1111 !
b1111 %
1"
#335
0"
#340
b0 !
b0 %
1"
#345
0"
#350
b1 !
b1 %
1"
#355
0"
#360
b10 !
b10 %
1"
#365
0"
#370
b11 !
b11 %
1"
#375
0"
#380
b100 !
b100 %
1"
#385
0"
#390
b101 !
b101 %
1"
#395
0"
#400
b110 !
b110 %
1"
#405
0"
#410
b111 !
b111 %
1"
#415
0"
#420
b1000 !
b1000 %
1"
#425
0"
#430
b1001 !
b1001 %
1"
#435
0"
#440
b1010 !
b1010 %
1"
#445
0"
#450
b1011 !
b1011 %
1"
#455
0"
#460
b1100 !
b1100 %
1"
#465
0"
#470
b1101 !
b1101 %
1"
#475
0"
#480
b1110 !
b1110 %
1"
#485
0"
#490
b1111 !
b1111 %
1"
#495
0"
#500
b0 !
b0 %
1"
#505
0"
#510
b1 !
b1 %
1"
