processor/CPU/program-counter/ProgramCounter.v
module ProgramCounter(clk, reset, pc);
  input clk, reset;

  output reg[31:0] pc;
  wire[31:0] pcNext;

  // pc adder
  assign #1 pcNext = pc + 4;

  // update pc
  always @(posedge clk) begin
    #1
    if(reset) pc = 0;
    else pc = pcNext;
  end
endmodule

processor/clock/Clock.v
module Clock(clk);
  output reg clk;

  initial begin
    clk = 1;
    forever begin
      #5 clk = ~clk;
    end
  end
endmodule

processor/CPU/program-counter/TestProgramCounter.v
`include "ProgramCounter.v"
`include "../../clock/Clock.v"

module TestProgramCounter;
  wire clk;
  reg reset;
  wire[31:0] pc;

  Clock clock(clk);
  ProgramCounter programCounter(clk, reset, pc);

  initial begin
    reset <= #15 1;
    reset <= #17 0;
 
    reset <= #76 1;
    reset <= #84 0;
   
    #500
    $finish;
  end

  // gtkWave
  initial begin 
    $dumpfile("TestProgramCounter.vcd");
    $dumpvars(0, TestProgramCounter);
  end

  // monitor
  initial begin
    $display();
    $display("********************  Test ProgramCounter  ********************");
    $display("\ttime\treset\tpc\tpcNext");
    $monitor("\t%4t\t%5d\t%2d\t%6d",$time, reset, pc, programCounter.pcNext); 
  end
endmodule

processor/CPU/program-counter/TestProgramCounter.vcd
$date
	Tue Oct 15 16:52:05 2024
$end
$version
	Icarus Verilog
$end
$timescale
	1s
$end
$scope module TestProgramCounter $end
$var wire 32 ! pc [31:0] $end
$var wire 1 " clk $end
$var reg 1 # reset $end
$scope module clock $end
$var reg 1 " clk $end
$upscope $end
$scope module programCounter $end
$var wire 1 " clk $end
$var wire 1 # reset $end
$var wire 32 $ pcNext [31:0] $end
$var reg 32 % pc [31:0] $end
$upscope $end
$upscope $end
$enddefinitions $end
$comment Show the parameter values. $end
$dumpall
$end
#0
$dumpvars
bx %
bx $
x#
1"
bx !
$end
#8
0"
#15
1#
#16
1"
#17
0#
b0 !
b0 %
#18
b100 $
#24
0"
#32
1"
#33
b100 !
b100 %
#34
b1000 $
#40
0"
#48
1"
#49
b1000 !
b1000 %
#50
b1100 $
#56
0"
#64
1"
#65
b1100 !
b1100 %
#66
b10000 $
#72
0"
#76
1#
#80
1"
#81
b0 !
b0 %
#82
b100 $
#84
0#
#88
0"
#96
1"
#97
b100 !
b100 %
#98
b1000 $
#104
0"
#112
1"
#113
b1000 !
b1000 %
#114
b1100 $
#120
0"
#128
1"
#129
b1100 !
b1100 %
#130
b10000 $
#136
0"
#144
1"
#145
b10000 !
b10000 %
#146
b10100 $
#152
0"
#160
1"
#161
b10100 !
b10100 %
#162
b11000 $
#168
0"
#176
1"
#177
b11000 !
b11000 %
#178
b11100 $
#184
0"
#192
1"
#193
b11100 !
b11100 %
#194
b100000 $
#200
0"
#208
1"
#209
b100000 !
b100000 %
#210
b100100 $
#216
0"
#224
1"
#225
b100100 !
b100100 %
#226
b101000 $
#232
0"
#240
1"
#241
b101000 !
b101000 %
#242
b101100 $
#248
0"
#256
1"
#257
b101100 !
b101100 %
#258
b110000 $
#264
0"
#272
1"
#273
b110000 !
b110000 %
#274
b110100 $
#280
0"
#288
1"
#289
b110100 !
b110100 %
#290
b111000 $
#296
0"
#304
1"
#305
b111000 !
b111000 %
#306
b111100 $
#312
0"
#320
1"
#321
b111100 !
b111100 %
#322
b1000000 $
#328
0"
#336
1"
#337
b1000000 !
b1000000 %
#338
b1000100 $
#344
0"
#352
1"
#353
b1000100 !
b1000100 %
#354
b1001000 $
#360
0"
#368
1"
#369
b1001000 !
b1001000 %
#370
b1001100 $
#376
0"
#384
1"
#385
b1001100 !
b1001100 %
#386
b1010000 $
#392
0"
#400
1"
#401
b1010000 !
b1010000 %
#402
b1010100 $
#408
0"
#416
1"
#417
b1010100 !
b1010100 %
#418
b1011000 $
#424
0"
#432
1"
#433
b1011000 !
b1011000 %
#434
b1011100 $
#440
0"
#448
1"
#449
b1011100 !
b1011100 %
#450
b1100000 $
#456
0"
#464
1"
#465
b1100000 !
b1100000 %
#466
b1100100 $
#472
0"
#480
1"
#481
b1100100 !
b1100100 %
#482
b1101000 $
#488
0"
#496
1"
#497
b1101000 !
b1101000 %
#498
b1101100 $
