processor/CPU/2s-complement/Negator.v
module Negator(in, out);
  input signed[7:0] in;
  output signed[7:0] out;

  assign #1 out = -in;
endmodule

processor/CPU/2s-complement/TestNegator.v
`include "Negator.v"

module TestNegator;
 reg signed[7:0] in;
 wire signed[7:0] out;

 Negator negator(in, out);

 initial begin
  #4
  in = 45;
  #4
  in = 20;
  #4
  in = -3;
  #4
  in = -48;
  #5
  $finish;
 end

 // gtkWave
  initial begin 
    $dumpfile("TestNegator.vcd");
    $dumpvars(0, TestNegator);
  end

  // monitor
  initial begin
    $display();
    $display("********************  Test Negator  ********************");
    $display("\ttime\tin\tout");
    $monitor("\t%4t\t%2d\t%3d",$time, in, out); 
  end

endmodule

processor/CPU/2s-complement/TestNegator.vcd
$date
	Tue Oct 15 14:59:06 2024
$end
$version
	Icarus Verilog
$end
$timescale
	1s
$end
$scope module TestNegator $end
$var wire 8 ! out [7:0] $end
$var reg 8 " in [7:0] $end
$scope module negator $end
$var wire 8 # in [7:0] $end
$var wire 8 $ out [7:0] $end
$upscope $end
$upscope $end
$enddefinitions $end
$comment Show the parameter values. $end
$dumpall
$end
#0
$dumpvars
bx $
bx #
bx "
bx !
$end
#4
b101101 "
b101101 #
#5
b11010011 !
b11010011 $
#8
b10100 "
b10100 #
#9
b11101100 !
b11101100 $
#12
b11111101 "
b11111101 #
#13
b11 !
b11 $
#16
b11010000 "
b11010000 #
#17
b110000 !
b110000 $
