processor/CPU/control-unit/ControlUnit.v
module ControlUnit(opcode, regWriteEnable, negate, aluSource, aluop);
  input[7:0] opcode;
  output reg[2:0] aluop;
  output reg regWriteEnable, negate, aluSource;

  always @(opcode) begin
    #1
    case (opcode)
      // loadi
      0: begin
        aluop = 0;
        aluSource = 0;
        negate = 1'bx;
        regWriteEnable = 1;
      end 
      // add
      1: begin
        aluop = 1;
        aluSource = 1;
        negate = 0;
        regWriteEnable = 1;
      end 
      // mov
      2: begin
        aluop = 0;
        aluSource = 1;
        negate = 0;
        regWriteEnable = 1;
      end 
      // sub
      3: begin
        aluop = 1;
        aluSource = 1;
        negate = 1;
        regWriteEnable = 1;
      end 
      // and
      4: begin
        aluop = 2;
        aluSource = 1;
        negate = 0;
        regWriteEnable = 1;
      end 
      // or
      5: begin
        aluop = 3;
        aluSource = 1;
        negate = 0;
        regWriteEnable = 1;
      end 
    endcase
  end
endmodule

processor/CPU/control-unit/TestControlUnit.v
`include "ControlUnit.v"

module TestControlUnit;
  reg[7:0] opcode;
  wire[2:0] aluop;
  wire regWriteEnable, negate, aluSource;

  ControlUnit controlUnit(opcode, regWriteEnable, negate, aluSource, aluop);

  initial begin
    #5
    opcode = 0;
    #5
    opcode = 1;
    #5
    opcode = 2;
    #5
    opcode = 3;
    #5
    opcode = 4;
    #5
    opcode = 5;
    #5
    $finish;
  end

  // gtkWave
  initial begin 
    $dumpfile("TestControlUnit.vcd");
    $dumpvars(0, TestControlUnit);
  end

  // monitor
  initial begin
    $display();
    $display("********************  Test ControlUnit  ********************");
    $display("\ttime\tOPCODE  \taluop\taluSource\tnegate\tregWriteEnable");
    $monitor("\t%4t\t%b\t%5b\t%9b\t%6b\t%14b",$time, opcode, aluop, aluSource, negate, regWriteEnable); 
  end
endmodule

processor/CPU/control-unit/TestControlUnit.vcd
$date
	Tue Oct 15 19:08:27 2024
$end
$version
	Icarus Verilog
$end
$timescale
	1s
$end
$scope module TestControlUnit $end
$var wire 1 ! regWriteEnable $end
$var wire 1 " negate $end
$var wire 3 # aluop [2:0] $end
$var wire 1 $ aluSource $end
$var reg 8 % opcode [7:0] $end
$scope module controlUnit $end
$var wire 8 & opcode [7:0] $end
$var reg 1 $ aluSource $end
$var reg 3 ' aluop [2:0] $end
$var reg 1 " negate $end
$var reg 1 ! regWriteEnable $end
$upscope $end
$upscope $end
$enddefinitions $end
$comment Show the parameter values. $end
$dumpall
$end
#0
$dumpvars
bx '
bx &
bx %
x$
bx #
x"
x!
$end
#5
b0 %
b0 &
#6
1!
0$
b0 #
b0 '
#10
b1 %
b1 &
#11
0"
1$
b1 #
b1 '
#15
b10 %
b10 &
#16
b0 #
b0 '
#20
b11 %
b11 &
#21
1"
b1 #
b1 '
#25
b100 %
b100 &
#26
0"
b10 #
b10 '
#30
b101 %
b101 &
#31
b11 #
b11 '
