processor/register-file/RegisterFile.v
module RegisterFile(dataIn, out1, out2, inAddress, out1Address, out2Address, write, clk, reset);
  input[7:0] dataIn; 
  input[2:0] inAddress, out1Address, out2Address;
  input write, clk, reset;
  output[7:0] out1, out2;

  reg[7:0] registerArray [7:0];
  
  // reading - async - #2
  assign #2 out1 = registerArray[out1Address];
  assign #2 out2 = registerArray[out2Address];

  // writing - sync -#1
  always @(posedge clk) begin
    #1
    if (write) registerArray[inAddress] = dataIn;
  end

  // resetting - sync -#1
  always @(posedge clk) begin
    #1
    if (reset) begin
      for (integer i = 0; i < 8; i++ ) begin
        registerArray[i] = 0;
      end
    end
  end
  
endmodule

processor/clock/Clock.v
module Clock(clk);
  output reg clk;

  initial begin
    clk = 1;
    forever begin
      #5 clk = ~clk;
    end
  end
endmodule

processor/register-file/TestRegisterFile.v
`include "../clock/Clock.v"
`include "RegisterFile.v"

module TestRegisterFile;
  reg[7:0] dataIn; 
  reg[2:0] inAddress, out1Address, out2Address;
  reg write, reset;
  wire clk;
  wire[7:0] out1, out2;

  // build the circuit
  Clock clock(clk);
  RegisterFile registerFile(dataIn, out1, out2, inAddress, out1Address, out2Address, write, clk, reset);


  // test
  initial begin
    // reset
    reset <= #8 1;
    reset <= #12 0;

    out1Address <= #13 0;
    out2Address <= #13 1;
    // The out1 and out2 values should be available at 15

    // set ro -> 5
    write <= #17 1;
    inAddress <= #17 0;
    dataIn <= #17 24;
    write <= #21 0;

    #40
    $finish;
    

    // set r0->24, r4->12
    // write <= #8 1;
    // inAddress <= #8 0;
    // dataIn <= #8 24;

    
  end


  // gtkWave
  initial begin 
    $dumpfile("TestRegisterFile.vcd");
    $dumpvars(0, TestRegisterFile);
    // dump the registerArray values
    for(integer i = 0; i < 8; i = i + 1) begin
      $dumpvars(1, registerFile.registerArray[i]);
    end
  end

  // monitor
  initial begin
    $display();
    $display("********************  TEST RegisterFile  ********************");
    $display("time\tr0\tr1\tr2\tr3\tr4\tr5\tr6\tr7\tout1Addr\tout2Addr\tinAddr\tdataIn\tout1\tout2\twrite\treset");
    $monitor("%4t\t%2d\t%2d\t%2d\t%2d\t%2d\t%2d\t%2d\t%2d\t%8d\t%8d\t%6d\t%6d\t%4d\t%4d\t%5d\t%5d", $time, registerFile.registerArray[0], registerFile.registerArray[1], registerFile.registerArray[2], registerFile.registerArray[3], registerFile.registerArray[4], registerFile.registerArray[5], registerFile.registerArray[6], registerFile.registerArray[7], out1Address, out2Address, inAddress, dataIn, out1, out2, write, reset); 
  end
endmodule

processor/register-file/TestRegisterFile.vcd
$date
	Mon Oct 14 12:43:49 2024
$end
$version
	Icarus Verilog
$end
$timescale
	1s
$end
$scope module TestRegisterFile $end
$var wire 8 ! out2 [7:0] $end
$var wire 8 " out1 [7:0] $end
$var wire 1 # clk $end
$var reg 8 $ dataIn [7:0] $end
$var reg 3 % inAddress [2:0] $end
$var reg 3 & out1Address [2:0] $end
$var reg 3 ' out2Address [2:0] $end
$var reg 1 ( reset $end
$var reg 1 ) write $end
$scope module clock $end
$var reg 1 # clk $end
$upscope $end
$scope module registerFile $end
$var wire 1 # clk $end
$var wire 8 * dataIn [7:0] $end
$var wire 3 + inAddress [2:0] $end
$var wire 8 , out1 [7:0] $end
$var wire 3 - out1Address [2:0] $end
$var wire 8 . out2 [7:0] $end
$var wire 3 / out2Address [2:0] $end
$var wire 1 ( reset $end
$var wire 1 ) write $end
$scope begin $ivl_for_loop0 $end
$var integer 32 0 i [31:0] $end
$upscope $end
$upscope $end
$scope begin $ivl_for_loop1 $end
$var integer 32 1 i [31:0] $end
$upscope $end
$upscope $end
$scope module TestRegisterFile $end
$scope module registerFile $end
$var reg 8 2 \registerArray[0] [7:0] $end
$upscope $end
$upscope $end
$scope module TestRegisterFile $end
$scope module registerFile $end
$var reg 8 3 \registerArray[1] [7:0] $end
$upscope $end
$upscope $end
$scope module TestRegisterFile $end
$scope module registerFile $end
$var reg 8 4 \registerArray[2] [7:0] $end
$upscope $end
$upscope $end
$scope module TestRegisterFile $end
$scope module registerFile $end
$var reg 8 5 \registerArray[3] [7:0] $end
$upscope $end
$upscope $end
$scope module TestRegisterFile $end
$scope module registerFile $end
$var reg 8 6 \registerArray[4] [7:0] $end
$upscope $end
$upscope $end
$scope module TestRegisterFile $end
$scope module registerFile $end
$var reg 8 7 \registerArray[5] [7:0] $end
$upscope $end
$upscope $end
$scope module TestRegisterFile $end
$scope module registerFile $end
$var reg 8 8 \registerArray[6] [7:0] $end
$upscope $end
$upscope $end
$scope module TestRegisterFile $end
$scope module registerFile $end
$var reg 8 9 \registerArray[7] [7:0] $end
$upscope $end
$upscope $end
$enddefinitions $end
$comment Show the parameter values. $end
$dumpall
$end
#0
$dumpvars
bx 9
bx 8
bx 7
bx 6
bx 5
bx 4
bx 3
bx 2
b1000 1
bx 0
bx /
bx .
bx -
bx ,
bx +
bx *
x)
x(
bx '
bx &
bx %
bx $
1#
bx "
bx !
$end
#5
0#
#8
1(
#10
1#
#11
b0 9
b0 8
b0 7
b0 6
b0 5
b0 4
b0 3
b0 2
b1000 0
#12
0(
#13
b1 '
b1 /
b0 &
b0 -
#15
b0 !
b0 .
b0 "
b0 ,
0#
#17
b11000 $
b11000 *
b0 %
b0 +
1)
#20
1#
#21
0)
b11000 2
#23
b11000 "
b11000 ,
